distilltime/__init__.py
distilltime-0.1.0.dist-info/LICENSE
distilltime-0.1.0.dist-info/METADATA
distilltime-0.1.0.dist-info/WHEEL
distilltime-0.1.0.dist-info/top_level.txt
distilltime-0.1.0.dist-info/RECORD
