Metadata-Version: 2.1
Name: distilltime
Version: 0.1.0
Summary: Distill Time is a model distillation framework for LLMs.
Author-email: Motoki Wu <tokestermw@gmail.com>
Requires-Python: >=3.9
License-File: LICENSE
